pushjack_http2_mod/__init__.py
pushjack_http2_mod/__version__.py
pushjack_http2_mod/_compat.py
pushjack_http2_mod/apns.py
pushjack_http2_mod/exceptions.py
pushjack_http2_mod/gcm.py
pushjack_http2_mod/utils.py
pushjack_http2_mod-1.0.3.dist-info/AUTHORS.rst
pushjack_http2_mod-1.0.3.dist-info/LICENSE.rst
pushjack_http2_mod-1.0.3.dist-info/METADATA
pushjack_http2_mod-1.0.3.dist-info/WHEEL
pushjack_http2_mod-1.0.3.dist-info/top_level.txt
pushjack_http2_mod-1.0.3.dist-info/RECORD
